virtualpulldown/__init__.py
virtualpulldown/cli.py
virtualpulldown/makefig_auto.py
virtualpulldown/run.py
virtualpulldown/v_pulldown_v2.py
virtualpulldown-0.2.5.dist-info/licenses/LICENSE
virtualpulldown-0.2.5.dist-info/METADATA
virtualpulldown-0.2.5.dist-info/WHEEL
virtualpulldown-0.2.5.dist-info/entry_points.txt
virtualpulldown-0.2.5.dist-info/top_level.txt
virtualpulldown-0.2.5.dist-info/RECORD
