Metadata-Version: 2.4
Name: virtualpulldown
Version: 0.2.5
Summary: A CLI tool for batch formatting protein pairs for structure prediction using LocalColabFold.
Author-email: Heewhan Shin <hshin40@gmail.com>
License: MIT
Project-URL: Homepage, https://github.com/heeropang/VirtualPulldown_v.2
Requires-Python: >=3.6
License-File: LICENSE
Requires-Dist: biopython
Requires-Dist: pandas
Requires-Dist: openpyxl
Requires-Dist: Pillow
Requires-Dist: numpy
Dynamic: license-file
